pythaiasr/__init__.py
pythaiasr-1.3.0.dist-info/LICENSE
pythaiasr-1.3.0.dist-info/METADATA
pythaiasr-1.3.0.dist-info/WHEEL
pythaiasr-1.3.0.dist-info/top_level.txt
pythaiasr-1.3.0.dist-info/RECORD
