Metadata-Version: 2.1
Name: pythaiasr
Version: 1.3.0
Summary: Python Thai ASR
Home-page: https://github.com/pythainlp/pythaiasr
Author: Wannaphong Phatthiyaphaibun
Author-email: wannaphong@yahoo.com
License: Apache Software License 2.0
Keywords: asr
Platform: UNKNOWN
Classifier: Development Status :: 5 - Production/Stable
Classifier: Intended Audience :: Developers
Classifier: Natural Language :: Thai
Classifier: License :: OSI Approved :: Apache Software License
Classifier: Operating System :: OS Independent
Classifier: Programming Language :: Python
Classifier: Programming Language :: Python :: 3
Classifier: Programming Language :: Python :: Implementation :: CPython
Classifier: Topic :: Scientific/Engineering
Requires-Dist: datasets
Requires-Dist: transformers (<5.0)
Requires-Dist: torchaudio
Requires-Dist: soundfile
Requires-Dist: torch
Requires-Dist: numpy
Provides-Extra: lm
Requires-Dist: pyctcdecode (>=0.4.0) ; extra == 'lm'
